LLM00/__init__.py
LLM00/test.py
LLM00-0.2.1.dist-info/METADATA
LLM00-0.2.1.dist-info/WHEEL
LLM00-0.2.1.dist-info/top_level.txt
LLM00-0.2.1.dist-info/RECORD
