Metadata-Version: 2.1
Name: LLM00
Version: 0.2.1
Summary: An interface that allows you to use LLMs in an ultra-simple way
Home-page: https://github.co.jp/
Author: bib_inf
Author-email: contact.bibinf@gmail.com
License: CC0 v1.0
Classifier: Programming Language :: Python :: 3
Classifier: Topic :: Software Development :: Libraries
Classifier: License :: CC0 1.0 Universal (CC0 1.0) Public Domain Dedication
Requires-Dist: ezpip
Requires-Dist: sout (>=1.2.1)
Requires-Dist: relpath
Requires-Dist: fies (>=1.4.0)
